rowmapy
